pyndex/__init__.py
pyndex/core/__init__.py
pyndex/core/algorithm.py
pyndex/core/index.py
pyndex/util/__init__.py
pyndex/util/_decorator.py
pyndex/util/diff.py
pyndex/util/join.py
pyndex_fin-0.1.2.dist-info/LICENSE
pyndex_fin-0.1.2.dist-info/METADATA
pyndex_fin-0.1.2.dist-info/WHEEL
pyndex_fin-0.1.2.dist-info/top_level.txt
pyndex_fin-0.1.2.dist-info/RECORD
