Metadata-Version: 2.1
Name: pyndex-fin
Version: 0.1.2
Summary: Pyndex: A python package for Russell index reconstruction.
Home-page: https://github.com/alemicheli/pyndex
Author: Alessandro Micheli
Author-email: am1118@imperial.ac.uk
License: UNKNOWN
Platform: UNKNOWN
Classifier: Programming Language :: Python :: 3
Classifier: License :: OSI Approved :: GNU General Public License v3 (GPLv3)
Classifier: Operating System :: OS Independent
Requires-Python: >=3.6
Requires-Dist: pandas (>=1.0.5)
Requires-Dist: wrds (>=3.0.8)
Requires-Dist: workalendar
